autohive_integrations_sdk/__init__.py
autohive_integrations_sdk/integration.py
autohive_integrations_sdk-0.1.4.dist-info/METADATA
autohive_integrations_sdk-0.1.4.dist-info/WHEEL
autohive_integrations_sdk-0.1.4.dist-info/licenses/LICENSE
autohive_integrations_sdk-0.1.4.dist-info/RECORD
