Metadata-Version: 2.4
Name: autohive_integrations_sdk
Version: 0.1.4
Summary: Integrations SDK for Autohive
Project-URL: Homepage, https://github.com/Autohive-AI/integrations-sdk
Project-URL: Issues, https://github.com/Autohive-AI/integrations-sdk/issues
Author-email: Hamish Taylor <hamish@autohive.com>, Reilly Oldham <reilly@autohive.com>, Kai Koenig <kai@autohive.com>
License-Expression: MIT
License-File: LICENSE
Classifier: Development Status :: 4 - Beta
Classifier: Intended Audience :: Developers
Classifier: Intended Audience :: System Administrators
Classifier: License :: OSI Approved :: MIT License
Classifier: Operating System :: OS Independent
Classifier: Programming Language :: Python :: 3
Classifier: Topic :: Scientific/Engineering :: Artificial Intelligence
Requires-Python: >=3.13
Requires-Dist: aiohttp
Requires-Dist: jsonschema==4.17.3
Requires-Dist: raygun4py>=6.0.1
